beancount_parser/__init__.py
beancount_parser/data_types.py
beancount_parser/grammar/account.lark
beancount_parser/grammar/beancount.lark
beancount_parser/grammar/boolean.lark
beancount_parser/grammar/comment.lark
beancount_parser/grammar/currency.lark
beancount_parser/grammar/date.lark
beancount_parser/grammar/escaped_string.lark
beancount_parser/grammar/flag.lark
beancount_parser/grammar/link.lark
beancount_parser/grammar/numbers.lark
beancount_parser/grammar/section_header.lark
beancount_parser/grammar/tag.lark
beancount_parser/helpers.py
beancount_parser/parser.py
beancount_parser-1.2.3.dist-info/LICENSE
beancount_parser-1.2.3.dist-info/METADATA
beancount_parser-1.2.3.dist-info/WHEEL
beancount_parser-1.2.3.dist-info/RECORD
